quranic_nlp/__init__.py
quranic_nlp/dependency_parsing.py
quranic_nlp/language.py
quranic_nlp/lemmatizer.py
quranic_nlp/postagger.py
quranic_nlp/root.py
quranic_nlp/utils.py
quranic_nlp-1.1.3.dist-info/LICENSE
quranic_nlp-1.1.3.dist-info/METADATA
quranic_nlp-1.1.3.dist-info/WHEEL
quranic_nlp-1.1.3.dist-info/top_level.txt
quranic_nlp-1.1.3.dist-info/RECORD
