Metadata-Version: 2.1
Name: quranic-nlp
Version: 1.1.3
Summary: quarnic nlp
Home-page: https://github.com/language-ml/hadith-quranic_nlp/
License-File: LICENSE
Requires-Dist: spacy
Requires-Dist: pandas
Requires-Dist: numpy
Requires-Dist: openpyxl
